nightjar/__init__.py
nightjar/base.py
nightjar/registry.py
nightjar/serializers.py
nightjar/utils.py
nightjar-0.0.7.dist-info/METADATA
nightjar-0.0.7.dist-info/WHEEL
nightjar-0.0.7.dist-info/licenses/LICENSE
nightjar-0.0.7.dist-info/RECORD
