Metadata-Version: 2.4
Name: nightjar
Version: 0.0.7
Summary: A typing based dispatching library.
Project-URL: Documentation, https://github.com/ysenarath/nightjar
Project-URL: Source, https://github.com/ysenarath/nightjar
Author-email: Yasas Senarath <email@example.com>
License-Expression: MIT
License-File: LICENSE
Keywords: dispatch,type-hinting,typing
Classifier: Development Status :: 2 - Pre-Alpha
Classifier: Programming Language :: Python
Classifier: Programming Language :: Python :: 3.9
Classifier: Programming Language :: Python :: 3.10
Classifier: Programming Language :: Python :: 3.11
Classifier: Programming Language :: Python :: Implementation :: CPython
Requires-Python: >=3.9
Requires-Dist: typing-extensions
